{
  "__inputs": [
    {
      "name": "DS_GITHUB_GOVERNANCE_BIGQUERY",
      "label": "GitHub Governance BigQuery",
      "description": "Select the configured Google BigQuery datasource that reads the github_governance dataset.",
      "type": "datasource",
      "pluginId": "grafana-bigquery-datasource",
      "pluginName": "Google BigQuery"
    }
  ],
  "__requires": [
    {
      "type": "grafana",
      "id": "grafana",
      "name": "Grafana",
      "version": "11.6.0"
    },
    {
      "type": "datasource",
      "id": "grafana-bigquery-datasource",
      "name": "Google BigQuery",
      "version": "3.0.0"
    },
    {
      "type": "panel",
      "id": "stat",
      "name": "Stat",
      "version": ""
    },
    {
      "type": "panel",
      "id": "timeseries",
      "name": "Time series",
      "version": ""
    },
    {
      "type": "panel",
      "id": "table",
      "name": "Table",
      "version": ""
    },
    {
      "type": "panel",
      "id": "text",
      "name": "Text",
      "version": ""
    }
  ],
  "annotations": {
    "list": []
  },
  "description": "Operational health dashboard for the GitHub Governance audit-log processor.",
  "editable": true,
  "fiscalYearStartMonth": 0,
  "graphTooltip": 1,
  "id": null,
  "links": [],
  "liveNow": false,
  "panels": [
    {
      "id": 1,
      "type": "text",
      "title": "Pipeline health scope",
      "gridPos": {
        "h": 3,
        "w": 24,
        "x": 0,
        "y": 0
      },
      "options": {
        "mode": "markdown",
        "content": "**GitHub Governance \u2014 Audit Pipeline Health**  \nTracks GitHub Enterprise audit-log ingestion from GCS into BigQuery: throughput, failures, parse quality, processing duration, and freshness. Non-audit `_check/` marker objects are excluded from health metrics. Source event lag may include historical backfill until backlog processing completes."
      },
      "pluginVersion": "11.6.0",
      "transparent": false
    },
    {
      "id": 2,
      "type": "stat",
      "title": "Last successful processing age",
      "description": "Seconds since the most recent successful audit-file processing run.",
      "datasource": {
        "type": "grafana-bigquery-datasource",
        "uid": "${DS_GITHUB_GOVERNANCE_BIGQUERY}"
      },
      "gridPos": {
        "h": 5,
        "w": 4,
        "x": 0,
        "y": 3
      },
      "fieldConfig": {
        "defaults": {
          "color": {
            "mode": "thresholds"
          },
          "mappings": [],
          "thresholds": {
            "mode": "absolute",
            "steps": [
              {
                "color": "green",
                "value": null
              },
              {
                "color": "orange",
                "value": 300
              },
              {
                "color": "red",
                "value": 900
              }
            ]
          },
          "unit": "s",
          "decimals": 0
        },
        "overrides": []
      },
      "options": {
        "reduceOptions": {
          "values": false,
          "calcs": [
            "lastNotNull"
          ],
          "fields": ""
        },
        "orientation": "auto",
        "textMode": "value_and_name",
        "colorMode": "value",
        "graphMode": "area",
        "justifyMode": "auto",
        "showPercentChange": false,
        "wideLayout": true
      },
      "pluginVersion": "11.6.0",
      "targets": [
        {
          "datasource": {
            "type": "grafana-bigquery-datasource",
            "uid": "${DS_GITHUB_GOVERNANCE_BIGQUERY}"
          },
          "editorMode": "code",
          "format": 1,
          "rawQuery": true,
          "rawSql": "SELECT\n              TIMESTAMP_DIFF(CURRENT_TIMESTAMP(), MAX(completed_at), SECOND) AS value\n            FROM `db-dev-l4to-mp-github.github_governance.github_audit_pipeline_health`\n            WHERE processing_status = 'SUCCESS'\n              AND NOT STARTS_WITH(source_file, '_check/')",
          "refId": "A",
          "project": "db-dev-l4to-mp-github"
        }
      ]
    },
    {
      "id": 3,
      "type": "stat",
      "title": "Files processed",
      "description": "File-level processing runs in the selected period.",
      "datasource": {
        "type": "grafana-bigquery-datasource",
        "uid": "${DS_GITHUB_GOVERNANCE_BIGQUERY}"
      },
      "gridPos": {
        "h": 5,
        "w": 4,
        "x": 4,
        "y": 3
      },
      "fieldConfig": {
        "defaults": {
          "color": {
            "mode": "thresholds"
          },
          "mappings": [],
          "thresholds": {
            "mode": "absolute",
            "steps": [
              {
                "color": "green",
                "value": null
              }
            ]
          },
          "unit": "short",
          "decimals": 0
        },
        "overrides": []
      },
      "options": {
        "reduceOptions": {
          "values": false,
          "calcs": [
            "lastNotNull"
          ],
          "fields": ""
        },
        "orientation": "auto",
        "textMode": "value_and_name",
        "colorMode": "value",
        "graphMode": "area",
        "justifyMode": "auto",
        "showPercentChange": false,
        "wideLayout": true
      },
      "pluginVersion": "11.6.0",
      "targets": [
        {
          "datasource": {
            "type": "grafana-bigquery-datasource",
            "uid": "${DS_GITHUB_GOVERNANCE_BIGQUERY}"
          },
          "editorMode": "code",
          "format": 1,
          "rawQuery": true,
          "rawSql": "SELECT COUNT(*) AS value\n            FROM `db-dev-l4to-mp-github.github_governance.github_audit_pipeline_health`\n            WHERE $__timeFilter(started_at)\n              AND NOT STARTS_WITH(source_file, '_check/')",
          "refId": "A",
          "project": "db-dev-l4to-mp-github"
        }
      ]
    },
    {
      "id": 4,
      "type": "stat",
      "title": "Events inserted",
      "description": "Normalized audit events written to BigQuery in the selected period.",
      "datasource": {
        "type": "grafana-bigquery-datasource",
        "uid": "${DS_GITHUB_GOVERNANCE_BIGQUERY}"
      },
      "gridPos": {
        "h": 5,
        "w": 4,
        "x": 8,
        "y": 3
      },
      "fieldConfig": {
        "defaults": {
          "color": {
            "mode": "thresholds"
          },
          "mappings": [],
          "thresholds": {
            "mode": "absolute",
            "steps": [
              {
                "color": "green",
                "value": null
              }
            ]
          },
          "unit": "short",
          "decimals": 0
        },
        "overrides": []
      },
      "options": {
        "reduceOptions": {
          "values": false,
          "calcs": [
            "lastNotNull"
          ],
          "fields": ""
        },
        "orientation": "auto",
        "textMode": "value_and_name",
        "colorMode": "value",
        "graphMode": "area",
        "justifyMode": "auto",
        "showPercentChange": false,
        "wideLayout": true
      },
      "pluginVersion": "11.6.0",
      "targets": [
        {
          "datasource": {
            "type": "grafana-bigquery-datasource",
            "uid": "${DS_GITHUB_GOVERNANCE_BIGQUERY}"
          },
          "editorMode": "code",
          "format": 1,
          "rawQuery": true,
          "rawSql": "SELECT COALESCE(SUM(events_inserted), 0) AS value\n            FROM `db-dev-l4to-mp-github.github_governance.github_audit_pipeline_health`\n            WHERE $__timeFilter(started_at)\n              AND NOT STARTS_WITH(source_file, '_check/')",
          "refId": "A",
          "project": "db-dev-l4to-mp-github"
        }
      ]
    },
    {
      "id": 5,
      "type": "stat",
      "title": "Pipeline success rate",
      "description": "Successful processing runs as a percentage of all real audit-file processing runs.",
      "datasource": {
        "type": "grafana-bigquery-datasource",
        "uid": "${DS_GITHUB_GOVERNANCE_BIGQUERY}"
      },
      "gridPos": {
        "h": 5,
        "w": 4,
        "x": 12,
        "y": 3
      },
      "fieldConfig": {
        "defaults": {
          "color": {
            "mode": "thresholds"
          },
          "mappings": [],
          "thresholds": {
            "mode": "absolute",
            "steps": [
              {
                "color": "red",
                "value": null
              },
              {
                "color": "orange",
                "value": 99.0
              },
              {
                "color": "green",
                "value": 99.9
              }
            ]
          },
          "unit": "percent",
          "decimals": 0
        },
        "overrides": []
      },
      "options": {
        "reduceOptions": {
          "values": false,
          "calcs": [
            "lastNotNull"
          ],
          "fields": ""
        },
        "orientation": "auto",
        "textMode": "value_and_name",
        "colorMode": "value",
        "graphMode": "area",
        "justifyMode": "auto",
        "showPercentChange": false,
        "wideLayout": true
      },
      "pluginVersion": "11.6.0",
      "targets": [
        {
          "datasource": {
            "type": "grafana-bigquery-datasource",
            "uid": "${DS_GITHUB_GOVERNANCE_BIGQUERY}"
          },
          "editorMode": "code",
          "format": 1,
          "rawQuery": true,
          "rawSql": "SELECT\n              SAFE_MULTIPLY(\n                SAFE_DIVIDE(\n                  COUNTIF(processing_status = 'SUCCESS'),\n                  COUNT(*)\n                ),\n                100\n              ) AS value\n            FROM `db-dev-l4to-mp-github.github_governance.github_audit_pipeline_health`\n            WHERE $__timeFilter(started_at)\n              AND NOT STARTS_WITH(source_file, '_check/')",
          "refId": "A",
          "project": "db-dev-l4to-mp-github"
        }
      ]
    },
    {
      "id": 6,
      "type": "stat",
      "title": "Failed files",
      "description": "Failed audit-file processing runs. Excludes _check/ marker objects.",
      "datasource": {
        "type": "grafana-bigquery-datasource",
        "uid": "${DS_GITHUB_GOVERNANCE_BIGQUERY}"
      },
      "gridPos": {
        "h": 5,
        "w": 4,
        "x": 16,
        "y": 3
      },
      "fieldConfig": {
        "defaults": {
          "color": {
            "mode": "thresholds"
          },
          "mappings": [],
          "thresholds": {
            "mode": "absolute",
            "steps": [
              {
                "color": "green",
                "value": null
              },
              {
                "color": "orange",
                "value": 1
              },
              {
                "color": "red",
                "value": 5
              }
            ]
          },
          "unit": "short",
          "decimals": 0
        },
        "overrides": []
      },
      "options": {
        "reduceOptions": {
          "values": false,
          "calcs": [
            "lastNotNull"
          ],
          "fields": ""
        },
        "orientation": "auto",
        "textMode": "value_and_name",
        "colorMode": "value",
        "graphMode": "area",
        "justifyMode": "auto",
        "showPercentChange": false,
        "wideLayout": true
      },
      "pluginVersion": "11.6.0",
      "targets": [
        {
          "datasource": {
            "type": "grafana-bigquery-datasource",
            "uid": "${DS_GITHUB_GOVERNANCE_BIGQUERY}"
          },
          "editorMode": "code",
          "format": 1,
          "rawQuery": true,
          "rawSql": "SELECT COUNTIF(processing_status = 'FAILED') AS value\n            FROM `db-dev-l4to-mp-github.github_governance.github_audit_pipeline_health`\n            WHERE $__timeFilter(started_at)\n              AND NOT STARTS_WITH(source_file, '_check/')",
          "refId": "A",
          "project": "db-dev-l4to-mp-github"
        }
      ]
    },
    {
      "id": 7,
      "type": "stat",
      "title": "Parse failures",
      "description": "Malformed or unparseable audit records. Excludes _check/ marker objects.",
      "datasource": {
        "type": "grafana-bigquery-datasource",
        "uid": "${DS_GITHUB_GOVERNANCE_BIGQUERY}"
      },
      "gridPos": {
        "h": 5,
        "w": 4,
        "x": 20,
        "y": 3
      },
      "fieldConfig": {
        "defaults": {
          "color": {
            "mode": "thresholds"
          },
          "mappings": [],
          "thresholds": {
            "mode": "absolute",
            "steps": [
              {
                "color": "green",
                "value": null
              },
              {
                "color": "orange",
                "value": 1
              },
              {
                "color": "red",
                "value": 10
              }
            ]
          },
          "unit": "short",
          "decimals": 0
        },
        "overrides": []
      },
      "options": {
        "reduceOptions": {
          "values": false,
          "calcs": [
            "lastNotNull"
          ],
          "fields": ""
        },
        "orientation": "auto",
        "textMode": "value_and_name",
        "colorMode": "value",
        "graphMode": "area",
        "justifyMode": "auto",
        "showPercentChange": false,
        "wideLayout": true
      },
      "pluginVersion": "11.6.0",
      "targets": [
        {
          "datasource": {
            "type": "grafana-bigquery-datasource",
            "uid": "${DS_GITHUB_GOVERNANCE_BIGQUERY}"
          },
          "editorMode": "code",
          "format": 1,
          "rawQuery": true,
          "rawSql": "SELECT COALESCE(SUM(parse_failures), 0) AS value\n            FROM `db-dev-l4to-mp-github.github_governance.github_audit_pipeline_health`\n            WHERE $__timeFilter(started_at)\n              AND NOT STARTS_WITH(source_file, '_check/')",
          "refId": "A",
          "project": "db-dev-l4to-mp-github"
        }
      ]
    },
    {
      "id": 8,
      "type": "timeseries",
      "title": "Events inserted over time",
      "description": "Audit event throughput written to BigQuery.",
      "datasource": {
        "type": "grafana-bigquery-datasource",
        "uid": "${DS_GITHUB_GOVERNANCE_BIGQUERY}"
      },
      "gridPos": {
        "h": 9,
        "w": 12,
        "x": 0,
        "y": 8
      },
      "fieldConfig": {
        "defaults": {
          "color": {
            "mode": "palette-classic"
          },
          "custom": {
            "axisCenteredZero": false,
            "axisColorMode": "text",
            "axisLabel": "",
            "axisPlacement": "auto",
            "barAlignment": 0,
            "drawStyle": "line",
            "fillOpacity": 12,
            "gradientMode": "none",
            "hideFrom": {
              "legend": false,
              "tooltip": false,
              "viz": false
            },
            "insertNulls": false,
            "lineInterpolation": "linear",
            "lineWidth": 2,
            "pointSize": 4,
            "scaleDistribution": {
              "type": "linear"
            },
            "showPoints": "auto",
            "spanNulls": false,
            "stacking": {
              "group": "A",
              "mode": "none"
            },
            "thresholdsStyle": {
              "mode": "off"
            }
          },
          "mappings": [],
          "thresholds": {
            "mode": "absolute",
            "steps": [
              {
                "color": "green",
                "value": null
              }
            ]
          },
          "unit": "short",
          "decimals": 0,
          "min": 0
        },
        "overrides": []
      },
      "options": {
        "legend": {
          "calcs": [],
          "displayMode": "list",
          "placement": "bottom",
          "showLegend": true
        },
        "tooltip": {
          "hideZeros": false,
          "mode": "single",
          "sort": "none"
        }
      },
      "pluginVersion": "11.6.0",
      "targets": [
        {
          "datasource": {
            "type": "grafana-bigquery-datasource",
            "uid": "${DS_GITHUB_GOVERNANCE_BIGQUERY}"
          },
          "editorMode": "code",
          "format": 0,
          "rawQuery": true,
          "rawSql": "SELECT\n              $__timeGroup(minute, $__interval) AS time,\n              SUM(events_inserted) AS events_inserted\n            FROM `db-dev-l4to-mp-github.github_governance.v_github_audit_pipeline_health_15m`\n            WHERE $__timeFilter(minute)\n            GROUP BY time\n            ORDER BY time",
          "refId": "A",
          "project": "db-dev-l4to-mp-github"
        }
      ]
    },
    {
      "id": 9,
      "type": "timeseries",
      "title": "Files processed over time",
      "description": "Real audit-file processing throughput. Failure trend is separated below for readability.",
      "datasource": {
        "type": "grafana-bigquery-datasource",
        "uid": "${DS_GITHUB_GOVERNANCE_BIGQUERY}"
      },
      "gridPos": {
        "h": 9,
        "w": 12,
        "x": 12,
        "y": 8
      },
      "fieldConfig": {
        "defaults": {
          "color": {
            "mode": "palette-classic"
          },
          "custom": {
            "axisCenteredZero": false,
            "axisColorMode": "text",
            "axisLabel": "",
            "axisPlacement": "auto",
            "barAlignment": 0,
            "drawStyle": "line",
            "fillOpacity": 12,
            "gradientMode": "none",
            "hideFrom": {
              "legend": false,
              "tooltip": false,
              "viz": false
            },
            "insertNulls": false,
            "lineInterpolation": "linear",
            "lineWidth": 2,
            "pointSize": 4,
            "scaleDistribution": {
              "type": "linear"
            },
            "showPoints": "auto",
            "spanNulls": false,
            "stacking": {
              "group": "A",
              "mode": "none"
            },
            "thresholdsStyle": {
              "mode": "off"
            }
          },
          "mappings": [],
          "thresholds": {
            "mode": "absolute",
            "steps": [
              {
                "color": "green",
                "value": null
              }
            ]
          },
          "unit": "short",
          "decimals": 0,
          "min": 0
        },
        "overrides": []
      },
      "options": {
        "legend": {
          "calcs": [],
          "displayMode": "list",
          "placement": "bottom",
          "showLegend": true
        },
        "tooltip": {
          "hideZeros": false,
          "mode": "single",
          "sort": "none"
        }
      },
      "pluginVersion": "11.6.0",
      "targets": [
        {
          "datasource": {
            "type": "grafana-bigquery-datasource",
            "uid": "${DS_GITHUB_GOVERNANCE_BIGQUERY}"
          },
          "editorMode": "code",
          "format": 0,
          "rawQuery": true,
          "rawSql": "SELECT\n              $__timeGroup(minute, $__interval) AS time,\n              SUM(files_processed) AS files_processed\n            FROM `db-dev-l4to-mp-github.github_governance.v_github_audit_pipeline_health_15m`\n            WHERE $__timeFilter(minute)\n            GROUP BY time\n            ORDER BY time",
          "refId": "A",
          "project": "db-dev-l4to-mp-github"
        }
      ]
    },
    {
      "id": 10,
      "type": "timeseries",
      "title": "p95 processing duration",
      "description": "p95 processor execution duration. Shown in milliseconds for better visibility.",
      "datasource": {
        "type": "grafana-bigquery-datasource",
        "uid": "${DS_GITHUB_GOVERNANCE_BIGQUERY}"
      },
      "gridPos": {
        "h": 9,
        "w": 12,
        "x": 0,
        "y": 17
      },
      "fieldConfig": {
        "defaults": {
          "color": {
            "mode": "palette-classic"
          },
          "custom": {
            "axisCenteredZero": false,
            "axisColorMode": "text",
            "axisLabel": "",
            "axisPlacement": "auto",
            "barAlignment": 0,
            "drawStyle": "line",
            "fillOpacity": 12,
            "gradientMode": "none",
            "hideFrom": {
              "legend": false,
              "tooltip": false,
              "viz": false
            },
            "insertNulls": false,
            "lineInterpolation": "linear",
            "lineWidth": 2,
            "pointSize": 4,
            "scaleDistribution": {
              "type": "linear"
            },
            "showPoints": "auto",
            "spanNulls": false,
            "stacking": {
              "group": "A",
              "mode": "none"
            },
            "thresholdsStyle": {
              "mode": "off"
            }
          },
          "mappings": [],
          "thresholds": {
            "mode": "absolute",
            "steps": [
              {
                "color": "green",
                "value": null
              }
            ]
          },
          "unit": "ms",
          "decimals": 0,
          "min": 0
        },
        "overrides": []
      },
      "options": {
        "legend": {
          "calcs": [],
          "displayMode": "list",
          "placement": "bottom",
          "showLegend": true
        },
        "tooltip": {
          "hideZeros": false,
          "mode": "single",
          "sort": "none"
        }
      },
      "pluginVersion": "11.6.0",
      "targets": [
        {
          "datasource": {
            "type": "grafana-bigquery-datasource",
            "uid": "${DS_GITHUB_GOVERNANCE_BIGQUERY}"
          },
          "editorMode": "code",
          "format": 0,
          "rawQuery": true,
          "rawSql": "SELECT\n              $__timeGroup(minute, $__interval) AS time,\n              MAX(p95_processing_duration_seconds) * 1000 AS p95_processing_duration_ms\n            FROM `db-dev-l4to-mp-github.github_governance.v_github_audit_pipeline_health_15m`\n            WHERE $__timeFilter(minute)\n            GROUP BY time\n            ORDER BY time",
          "refId": "A",
          "project": "db-dev-l4to-mp-github"
        }
      ]
    },
    {
      "id": 11,
      "type": "timeseries",
      "title": "Pipeline failures over time",
      "description": "Failures, partial failures, and parse failures. Excludes _check/ marker objects.",
      "datasource": {
        "type": "grafana-bigquery-datasource",
        "uid": "${DS_GITHUB_GOVERNANCE_BIGQUERY}"
      },
      "gridPos": {
        "h": 9,
        "w": 12,
        "x": 12,
        "y": 17
      },
      "fieldConfig": {
        "defaults": {
          "color": {
            "mode": "palette-classic"
          },
          "custom": {
            "axisCenteredZero": false,
            "axisColorMode": "text",
            "axisLabel": "",
            "axisPlacement": "auto",
            "barAlignment": 0,
            "drawStyle": "line",
            "fillOpacity": 12,
            "gradientMode": "none",
            "hideFrom": {
              "legend": false,
              "tooltip": false,
              "viz": false
            },
            "insertNulls": false,
            "lineInterpolation": "linear",
            "lineWidth": 2,
            "pointSize": 4,
            "scaleDistribution": {
              "type": "linear"
            },
            "showPoints": "auto",
            "spanNulls": false,
            "stacking": {
              "group": "A",
              "mode": "none"
            },
            "thresholdsStyle": {
              "mode": "off"
            }
          },
          "mappings": [],
          "thresholds": {
            "mode": "absolute",
            "steps": [
              {
                "color": "green",
                "value": null
              }
            ]
          },
          "unit": "short",
          "decimals": 0,
          "min": 0
        },
        "overrides": []
      },
      "options": {
        "legend": {
          "calcs": [],
          "displayMode": "list",
          "placement": "bottom",
          "showLegend": true
        },
        "tooltip": {
          "hideZeros": false,
          "mode": "single",
          "sort": "none"
        }
      },
      "pluginVersion": "11.6.0",
      "targets": [
        {
          "datasource": {
            "type": "grafana-bigquery-datasource",
            "uid": "${DS_GITHUB_GOVERNANCE_BIGQUERY}"
          },
          "editorMode": "code",
          "format": 0,
          "rawQuery": true,
          "rawSql": "SELECT\n              $__timeGroup(started_at, $__interval) AS time,\n              COUNTIF(processing_status = 'FAILED') AS failed_files,\n              COUNTIF(processing_status = 'PARTIAL_FAILURE') AS partial_failure_files,\n              SUM(parse_failures) AS parse_failures\n            FROM `db-dev-l4to-mp-github.github_governance.github_audit_pipeline_health`\n            WHERE $__timeFilter(started_at)\n              AND NOT STARTS_WITH(source_file, '_check/')\n            GROUP BY time\n            ORDER BY time",
          "refId": "A",
          "project": "db-dev-l4to-mp-github"
        }
      ]
    },
    {
      "id": 12,
      "type": "timeseries",
      "title": "Source event lag \u2014 historical backfill included",
      "description": "Lag between source event time and processing completion. Historical backfill can increase this temporarily.",
      "datasource": {
        "type": "grafana-bigquery-datasource",
        "uid": "${DS_GITHUB_GOVERNANCE_BIGQUERY}"
      },
      "gridPos": {
        "h": 8,
        "w": 12,
        "x": 0,
        "y": 26
      },
      "fieldConfig": {
        "defaults": {
          "color": {
            "mode": "palette-classic"
          },
          "custom": {
            "axisCenteredZero": false,
            "axisColorMode": "text",
            "axisLabel": "",
            "axisPlacement": "auto",
            "barAlignment": 0,
            "drawStyle": "line",
            "fillOpacity": 12,
            "gradientMode": "none",
            "hideFrom": {
              "legend": false,
              "tooltip": false,
              "viz": false
            },
            "insertNulls": false,
            "lineInterpolation": "linear",
            "lineWidth": 2,
            "pointSize": 4,
            "scaleDistribution": {
              "type": "linear"
            },
            "showPoints": "auto",
            "spanNulls": false,
            "stacking": {
              "group": "A",
              "mode": "none"
            },
            "thresholdsStyle": {
              "mode": "off"
            }
          },
          "mappings": [],
          "thresholds": {
            "mode": "absolute",
            "steps": [
              {
                "color": "green",
                "value": null
              }
            ]
          },
          "unit": "s",
          "decimals": 0,
          "min": 0
        },
        "overrides": []
      },
      "options": {
        "legend": {
          "calcs": [],
          "displayMode": "list",
          "placement": "bottom",
          "showLegend": true
        },
        "tooltip": {
          "hideZeros": false,
          "mode": "single",
          "sort": "none"
        }
      },
      "pluginVersion": "11.6.0",
      "targets": [
        {
          "datasource": {
            "type": "grafana-bigquery-datasource",
            "uid": "${DS_GITHUB_GOVERNANCE_BIGQUERY}"
          },
          "editorMode": "code",
          "format": 0,
          "rawQuery": true,
          "rawSql": "SELECT\n              $__timeGroup(minute, $__interval) AS time,\n              MAX(avg_source_event_lag_seconds) AS source_event_lag_seconds\n            FROM `db-dev-l4to-mp-github.github_governance.v_github_audit_pipeline_health_15m`\n            WHERE $__timeFilter(minute)\n            GROUP BY time\n            ORDER BY time",
          "refId": "A",
          "project": "db-dev-l4to-mp-github"
        }
      ]
    },
    {
      "id": 13,
      "type": "stat",
      "title": "Duplicates skipped",
      "description": "Duplicates removed within source files. Expected for at-least-once delivery.",
      "datasource": {
        "type": "grafana-bigquery-datasource",
        "uid": "${DS_GITHUB_GOVERNANCE_BIGQUERY}"
      },
      "gridPos": {
        "h": 5,
        "w": 4,
        "x": 12,
        "y": 26
      },
      "fieldConfig": {
        "defaults": {
          "color": {
            "mode": "thresholds"
          },
          "mappings": [],
          "thresholds": {
            "mode": "absolute",
            "steps": [
              {
                "color": "green",
                "value": null
              }
            ]
          },
          "unit": "short",
          "decimals": 0
        },
        "overrides": []
      },
      "options": {
        "reduceOptions": {
          "values": false,
          "calcs": [
            "lastNotNull"
          ],
          "fields": ""
        },
        "orientation": "auto",
        "textMode": "value_and_name",
        "colorMode": "value",
        "graphMode": "area",
        "justifyMode": "auto",
        "showPercentChange": false,
        "wideLayout": true
      },
      "pluginVersion": "11.6.0",
      "targets": [
        {
          "datasource": {
            "type": "grafana-bigquery-datasource",
            "uid": "${DS_GITHUB_GOVERNANCE_BIGQUERY}"
          },
          "editorMode": "code",
          "format": 1,
          "rawQuery": true,
          "rawSql": "SELECT COALESCE(SUM(duplicates_skipped), 0) AS value\n            FROM `db-dev-l4to-mp-github.github_governance.github_audit_pipeline_health`\n            WHERE $__timeFilter(started_at)\n              AND NOT STARTS_WITH(source_file, '_check/')",
          "refId": "A",
          "project": "db-dev-l4to-mp-github"
        }
      ]
    },
    {
      "id": 14,
      "type": "table",
      "title": "Recent failed audit files",
      "description": "Excludes non-audit _check/ marker objects.",
      "datasource": {
        "type": "grafana-bigquery-datasource",
        "uid": "${DS_GITHUB_GOVERNANCE_BIGQUERY}"
      },
      "gridPos": {
        "h": 11,
        "w": 24,
        "x": 0,
        "y": 34
      },
      "fieldConfig": {
        "defaults": {
          "color": {
            "mode": "thresholds"
          },
          "custom": {
            "align": "auto",
            "cellOptions": {
              "type": "auto"
            },
            "filterable": true,
            "inspect": false,
            "minWidth": 80
          },
          "mappings": [],
          "thresholds": {
            "mode": "absolute",
            "steps": [
              {
                "color": "green",
                "value": null
              }
            ]
          }
        },
        "overrides": [
          {
            "matcher": {
              "id": "byName",
              "options": "source_file"
            },
            "properties": [
              {
                "id": "custom.width",
                "value": 360
              },
              {
                "id": "custom.cellOptions",
                "value": {
                  "type": "auto",
                  "wrapText": true
                }
              }
            ]
          },
          {
            "matcher": {
              "id": "byName",
              "options": "error_message"
            },
            "properties": [
              {
                "id": "custom.width",
                "value": 520
              },
              {
                "id": "custom.cellOptions",
                "value": {
                  "type": "auto",
                  "wrapText": true
                }
              }
            ]
          }
        ]
      },
      "options": {
        "cellHeight": "sm",
        "showHeader": true,
        "sortBy": [
          {
            "desc": true,
            "displayName": "started_at"
          }
        ]
      },
      "pluginVersion": "11.6.0",
      "targets": [
        {
          "datasource": {
            "type": "grafana-bigquery-datasource",
            "uid": "${DS_GITHUB_GOVERNANCE_BIGQUERY}"
          },
          "editorMode": "code",
          "format": 1,
          "rawQuery": true,
          "rawSql": "SELECT\n              started_at,\n              source_file,\n              processing_status,\n              events_seen,\n              events_inserted,\n              duplicates_skipped,\n              parse_failures,\n              processing_duration_seconds,\n              source_event_lag_seconds,\n              error_message\n            FROM `db-dev-l4to-mp-github.github_governance.v_github_audit_pipeline_failures`\n            WHERE $__timeFilter(started_at)\n              AND NOT STARTS_WITH(source_file, '_check/')\n            ORDER BY started_at DESC\n            LIMIT 100",
          "refId": "A",
          "project": "db-dev-l4to-mp-github"
        }
      ]
    }
  ],
  "refresh": "5m",
  "schemaVersion": 41,
  "tags": [
    "github",
    "governance",
    "audit-logs",
    "pipeline-health",
    "bigquery"
  ],
  "templating": {
    "list": []
  },
  "time": {
    "from": "now-24h",
    "to": "now"
  },
  "timepicker": {},
  "timezone": "utc",
  "title": "GitHub Governance \u2014 Audit Pipeline Health",
  "uid": "github-governance-pipeline-health",
  "version": 2,
  "weekStart": ""
}
